Metadata-Version: 2.1
Name: paramrule
Version: 0.0.2
Summary: Python parameter verification tool class.
Home-page: https://github.com/Lyo-Shur/paramrule
Author: Lyo-Shur
Author-email: 1421333878@qq.com
Maintainer: Lyo-Shur
Maintainer-email: 1421333878@qq.com
License: MIT License
Keywords: param verification
Platform: ubuntu
Platform: windows
Classifier: Development Status :: 4 - Beta
Classifier: Operating System :: OS Independent
Classifier: Intended Audience :: Developers
Classifier: License :: OSI Approved :: MIT License
Classifier: Programming Language :: Python
Classifier: Programming Language :: Python :: Implementation
Classifier: Programming Language :: Python :: 3.4
Classifier: Programming Language :: Python :: 3.5
Classifier: Programming Language :: Python :: 3.6
Classifier: Programming Language :: Python :: 3.7
Classifier: Programming Language :: Python :: 3.8
Classifier: Topic :: Software Development :: Libraries
